rosetta_search/__init__.py
rosetta_search/cli.py
rosetta_search/database.py
rosetta_search/nlp_server.py
rosetta_search/nlp_utils.py
rosetta_search/rosetta_index.py
rosetta_search/utils.py
rosetta_search-0.0.7.dist-info/LICENSE.txt
rosetta_search-0.0.7.dist-info/METADATA
rosetta_search-0.0.7.dist-info/WHEEL
rosetta_search-0.0.7.dist-info/entry_points.txt
rosetta_search-0.0.7.dist-info/top_level.txt
rosetta_search-0.0.7.dist-info/RECORD
